{
    "props": {
        "pageProps": {
            "reviewCount": 4,
            "careerPathData": {
                "value": {
                    "jobTitle": "Search Engine Optimization (SEO) Director",
                    "url": "/research/US/Job=Search_Engine_Optimization_(SEO)_Director/Salary",
                    "compensation": 93513.84700210099,
                    "isHourly": false,
                    "currency": "USD"
                },
                "childCount": 1,
                "children": [
                    {
                        "index": 0,
                        "value": {
                            "jobTitle": "Marketing Director",
                            "url": "/research/US/Job=Marketing_Director/Salary",
                            "percent": 1,
                            "compensation": 87911.19122321739,
                            "isHourly": false,
                            "currency": "USD"
                        },
                        "childCount": 3,
                        "children": [
                            {
                                "index": 0,
                                "value": {
                                    "jobTitle": "Vice President (VP), Marketing",
                                    "url": "/research/US/Job=Vice_President_(VP)%2C_Marketing/Salary",
                                    "percent": 0.17,
                                    "compensation": 147315.7577942771,
                                    "isHourly": false,
                                    "currency": "USD"
                                }
                            },
                            {
                                "index": 1,
                                "value": {
                                    "jobTitle": "Marketing Manager",
                                    "url": "/research/US/Job=Marketing_Manager/Salary",
                                    "percent": 0.07,
                                    "compensation": 65377.345493279194,
                                    "isHourly": false,
                                    "currency": "USD"
                                }
                            },
                            {
                                "index": 2,
                                "value": {
                                    "jobTitle": "Chief Marketing Officer (CMO)",
                                    "url": "/research/US/Job=Chief_Marketing_Officer_(CMO)/Salary",
                                    "percent": 0.04,
                                    "compensation": 173998.04958740273,
                                    "isHourly": false,
                                    "currency": "USD"
                                }
                            }
                        ]
                    }
                ]
            },
            "siteUrl": "https://www.payscale.com",
            "pageData": {
                "country": "US",
                "category": "Job",
                "dimensions": {
                    "job": "Search Engine Optimization (SEO) Director"
                },
                "multiDimensional": false,
                "reportType": "Salary",
                "refs": {
                    "url": "/research/US/Job=Search_Engine_Optimization_(SEO)_Director/Salary",
                    "defaultUrl": "/research/US/Job=Search_Engine_Optimization_(SEO)_Director/Salary",
                    "parentUrl": null
                },
                "currencyCode": "USD",
                "lastUpdated": "2023-08-09T10:08:12.38749Z",
                "narratives": {
                    "description": "Search engine optimization (SEO) directors serve as innovators and often work in teams to brainstorm ideas for improving SEO for an organization's online presence. They are primarily responsible for supervising SEO employees and typically work in office settings, and attending meetings may be necessary on a regular basis.\r\nSEO directors work with a variety of staff, particularly project managers, so strong communication skills are important in this position, and many directors work for large tech companies such as Google, Microsoft, and Yahoo.\r\nA bachelor's degree in information technology (IT) or a related field and at least a few years of relevant experience are generally required for this position, and some employers may prefer those who also have prior leadership experience. Computer skills and proficiency in Microsoft Office programs are essential in this position, and strong communication skills are also important to work well with staff members and achieve goals in a timely manner. SEO directors typically work full-time, and some overtime may be necessary on occasion, so the ability to work under pressure and strict deadlines is highly beneficial.",
                    "summaryHourly": "The average pay for a Search Engine Optimization (SEO) Director is $34.74 per hour.",
                    "summarySalary": "The average pay for a Search Engine Optimization (SEO) Director is $96,416 per year."
                },
                "tasks": [
                    "Develop and drive strategies to maximize an organization's SEO performance.",
                    "Collaborate strongly with taxonomists and back-end technology experts to create a robust data infrastructure.",
                    "Monitor trends in search engine prioritization and collaborate across departments to take advantage of opportunities with current and future online strategies.",
                    "Assemble a team of SEO analysts and facilitate healthy organization and communication."
                ],
                "compensation": {
                    "bonus": {
                        "10": 1089.06,
                        "25": 2350,
                        "50": 7428.11,
                        "75": 13500,
                        "90": 29021.02,
                        "profileCount": 25
                    },
                    "hourlyRate": {
                        "50": 34.74,
                        "profileCount": 4
                    },
                    "salary": {
                        "10": 64779.27,
                        "25": 78937.02,
                        "50": 96416.2,
                        "75": 120439.17,
                        "90": 146993.54,
                        "profileCount": 82
                    },
                    "total": {
                        "10": 64114.93,
                        "25": 80714.39,
                        "50": 99421.81,
                        "75": 119907.06,
                        "90": 150032.23,
                        "profileCount": 86
                    }
                },
                "byDimension": {
                    "Average EAC Overall": {
                        "lastUpdated": "2023-08-09T10:08:12.38749Z",
                        "profileCount": 86,
                        "description": "Effective Annual Compensation",
                        "rows": [
                            {
                                "name": "Main",
                                "displayName": null,
                                "url": null,
                                "profileCount": 86,
                                "range": {
                                    "10": 64114.93,
                                    "25": 80714.39,
                                    "50": 99421.81,
                                    "75": 119907.06,
                                    "90": 150032.23
                                },
                                "isEstimated": false
                            }
                        ],
                        "parentUrl": null
                    },
                    "Average Hourly Rate Overall": {
                        "lastUpdated": "2023-08-09T10:08:12.38749Z",
                        "profileCount": 4,
                        "description": "Hourly Rate",
                        "rows": [
                            {
                                "name": "Main",
                                "displayName": null,
                                "url": null,
                                "profileCount": 4,
                                "range": {
                                    "50": 34.74
                                },
                                "isEstimated": true
                            }
                        ],
                        "parentUrl": null
                    },
                    "Average Salary Overall": {
                        "lastUpdated": "2023-08-09T10:08:12.38749Z",
                        "profileCount": 82,
                        "description": "Salary",
                        "rows": [
                            {
                                "name": "Main",
                                "displayName": null,
                                "url": null,
                                "profileCount": 82,
                                "range": {
                                    "10": 64779.27,
                                    "25": 78937.02,
                                    "50": 96416.2,
                                    "75": 120439.17,
                                    "90": 146993.54
                                },
                                "isEstimated": false
                            }
                        ],
                        "parentUrl": null
                    },
                    "Gender Breakdown": {
                        "lastUpdated": "2023-08-09T10:08:12.38749Z",
                        "profileCount": 36,
                        "description": "Gender Breakdown",
                        "rows": [
                            {
                                "name": "Female",
                                "displayName": null,
                                "url": null,
                                "profileCount": 18,
                                "range": null,
                                "isEstimated": false
                            },
                            {
                                "name": "Male",
                                "displayName": null,
                                "url": null,
                                "profileCount": 18,
                                "range": null,
                                "isEstimated": false
                            }
                        ],
                        "parentUrl": null
                    },
                    "Health Insurance Overall": {
                        "lastUpdated": "2023-08-09T10:08:12.38749Z",
                        "profileCount": 47,
                        "description": "Health Benefits",
                        "rows": [
                            {
                                "name": "Medical / Health",
                                "displayName": null,
                                "url": null,
                                "profileCount": 40,
                                "range": null,
                                "isEstimated": false
                            },
                            {
                                "name": "Dental",
                                "displayName": null,
                                "url": null,
                                "profileCount": 36,
                                "range": null,
                                "isEstimated": false
                            },
                            {
                                "name": "Vision",
                                "displayName": null,
                                "url": null,
                                "profileCount": 32,
                                "range": null,
                                "isEstimated": false
                            },
                            {
                                "name": "None",
                                "displayName": null,
                                "url": null,
                                "profileCount": 7,
                                "range": null,
                                "isEstimated": false
                            }
                        ],
                        "parentUrl": null
                    },
                    "Job by Employer": {
                        "lastUpdated": null,
                        "profileCount": null,
                        "description": "Job by Employer",
                        "rows": [],
                        "parentUrl": null
                    },
                    "Job by Experience": {
                        "lastUpdated": null,
                        "profileCount": null,
                        "description": "Job by Experience",
                        "rows": [
                            {
                                "name": "1-4 years",
                                "displayName": null,
                                "url": "/research/US/Job=Search_Engine_Optimization_(SEO)_Director/Salary/66d44c5f/Early-Career",
                                "profileCount": 14,
                                "range": {
                                    "50": 79734.45
                                },
                                "isEstimated": null
                            },
                            {
                                "name": "5-9 years",
                                "displayName": null,
                                "url": "/research/US/Job=Search_Engine_Optimization_(SEO)_Director/Salary/7217ee04/Mid-Career",
                                "profileCount": 51,
                                "range": {
                                    "50": 99134.61
                                },
                                "isEstimated": null
                            },
                            {
                                "name": "10-19 years",
                                "displayName": null,
                                "url": "/research/US/Job=Search_Engine_Optimization_(SEO)_Director/Salary/b93b16b7/Experienced",
                                "profileCount": 42,
                                "range": {
                                    "50": 108999.71
                                },
                                "isEstimated": null
                            },
                            {
                                "name": "20 years or more",
                                "displayName": null,
                                "url": "/research/US/Job=Search_Engine_Optimization_(SEO)_Director/Salary/468689f8/Late-Career",
                                "profileCount": 8,
                                "range": {
                                    "50": 96448.2
                                },
                                "isEstimated": null
                            }
                        ],
                        "parentUrl": null
                    },
                    "Job by Location": {
                        "lastUpdated": null,
                        "profileCount": null,
                        "description": "Job by Location",
                        "rows": [
                            {
                                "name": "New York, New York",
                                "displayName": null,
                                "url": "/research/US/Job=Search_Engine_Optimization_(SEO)_Director/Salary/3e9d496c/New-York-NY",
                                "profileCount": 10,
                                "range": {
                                    "50": 142162.09
                                },
                                "isEstimated": null
                            },
                            {
                                "name": "San Diego, California",
                                "displayName": null,
                                "url": "/research/US/Job=Search_Engine_Optimization_(SEO)_Director/Salary/4155fc8f/San-Diego-CA",
                                "profileCount": 9,
                                "range": {
                                    "50": 100000
                                },
                                "isEstimated": null
                            },
                            {
                                "name": "Chicago, Illinois",
                                "displayName": null,
                                "url": "/research/US/Job=Search_Engine_Optimization_(SEO)_Director/Salary/043fa8f7/Chicago-IL",
                                "profileCount": 8,
                                "range": {
                                    "50": 108500
                                },
                                "isEstimated": null
                            },
                            {
                                "name": "Los Angeles, California",
                                "displayName": null,
                                "url": "/research/US/Job=Search_Engine_Optimization_(SEO)_Director/Salary/00711f95/Los-Angeles-CA",
                                "profileCount": 5,
                                "range": {
                                    "50": 124775.11
                                },
                                "isEstimated": null
                            },
                            {
                                "name": "San Francisco, California",
                                "displayName": null,
                                "url": "/research/US/Job=Search_Engine_Optimization_(SEO)_Director/Salary/3a629b3e/San-Francisco-CA",
                                "profileCount": 5,
                                "range": {
                                    "50": 137454.55
                                },
                                "isEstimated": null
                            },
                            {
                                "name": "Miami, Florida",
                                "displayName": null,
                                "url": "/research/US/Job=Search_Engine_Optimization_(SEO)_Director/Salary/3cfe8a74/Miami-FL",
                                "profileCount": 5,
                                "range": {
                                    "50": 85000
                                },
                                "isEstimated": null
                            },
                            {
                                "name": "Portland, Oregon",
                                "displayName": null,
                                "url": "/research/US/Job=Search_Engine_Optimization_(SEO)_Director/Salary/da0b7a28/Portland-OR",
                                "profileCount": 5,
                                "range": {
                                    "50": 91562.83
                                },
                                "isEstimated": null
                            },
                            {
                                "name": "Atlanta, Georgia",
                                "displayName": null,
                                "url": "/research/US/Job=Search_Engine_Optimization_(SEO)_Director/Salary/ff783331/Atlanta-GA",
                                "profileCount": 5,
                                "range": {
                                    "50": 94500
                                },
                                "isEstimated": null
                            },
                            {
                                "name": "Seattle, Washington",
                                "displayName": null,
                                "url": "/research/US/Job=Search_Engine_Optimization_(SEO)_Director/Salary/de983e16/Seattle-WA",
                                "profileCount": 4,
                                "range": {
                                    "50": 99750
                                },
                                "isEstimated": null
                            },
                            {
                                "name": "Philadelphia, Pennsylvania",
                                "displayName": null,
                                "url": "/research/US/Job=Search_Engine_Optimization_(SEO)_Director/Salary/fe4066b8/Philadelphia-PA",
                                "profileCount": 2,
                                "range": {
                                    "50": 107000
                                },
                                "isEstimated": null
                            }
                        ],
                        "parentUrl": null
                    },
                    "Job by Skill": {
                        "lastUpdated": null,
                        "profileCount": null,
                        "description": "Job by Skill",
                        "rows": [
                            {
                                "name": "Search Engine Optimization (SEO)",
                                "displayName": null,
                                "url": "/research/US/Job=Search_Engine_Optimization_(SEO)_Director/Salary/cbae0fee/Search-Engine-Optimization-SEO",
                                "profileCount": 86,
                                "range": {
                                    "50": 99843.46
                                },
                                "isEstimated": null
                            },
                            {
                                "name": "Team Leadership",
                                "displayName": null,
                                "url": "/research/US/Job=Search_Engine_Optimization_(SEO)_Director/Salary/637dd4f6/Team-Leadership",
                                "profileCount": 50,
                                "range": {
                                    "50": 98575.35
                                },
                                "isEstimated": null
                            },
                            {
                                "name": "Strategy",
                                "displayName": null,
                                "url": "/research/US/Job=Search_Engine_Optimization_(SEO)_Director/Salary/4a4f9403/Strategy",
                                "profileCount": 41,
                                "range": {
                                    "50": 102433.31
                                },
                                "isEstimated": null
                            },
                            {
                                "name": "Google Analytics",
                                "displayName": null,
                                "url": "/research/US/Job=Search_Engine_Optimization_(SEO)_Director/Salary/22a89851/Google-Analytics",
                                "profileCount": 29,
                                "range": {
                                    "50": 92432.43
                                },
                                "isEstimated": null
                            },
                            {
                                "name": "Web Analytics",
                                "displayName": null,
                                "url": "/research/US/Job=Search_Engine_Optimization_(SEO)_Director/Salary/f7e55982/Web-Analytics",
                                "profileCount": 21,
                                "range": {
                                    "50": 96649.66
                                },
                                "isEstimated": null
                            },
                            {
                                "name": "Online Marketing",
                                "displayName": null,
                                "url": "/research/US/Job=Search_Engine_Optimization_(SEO)_Director/Salary/64c46820/Online-Marketing",
                                "profileCount": 12,
                                "range": {
                                    "50": 87428.57
                                },
                                "isEstimated": null
                            },
                            {
                                "name": "Project Management",
                                "displayName": null,
                                "url": "/research/US/Job=Search_Engine_Optimization_(SEO)_Director/Salary/11a76ee3/Project-Management",
                                "profileCount": 11,
                                "range": {
                                    "50": 105000
                                },
                                "isEstimated": null
                            },
                            {
                                "name": "Search Engine Marketing (SEM)",
                                "displayName": null,
                                "url": "/research/US/Job=Search_Engine_Optimization_(SEO)_Director/Salary/eb006ae8/Search-Engine-Marketing-SEM",
                                "profileCount": 8,
                                "range": {
                                    "50": 93350.34
                                },
                                "isEstimated": null
                            },
                            {
                                "name": "People Management",
                                "displayName": null,
                                "url": "/research/US/Job=Search_Engine_Optimization_(SEO)_Director/Salary/587b753b/People-Management",
                                "profileCount": 5,
                                "range": {
                                    "50": 88437.17
                                },
                                "isEstimated": null
                            },
                            {
                                "name": "Content Management",
                                "displayName": null,
                                "url": "/research/US/Job=Search_Engine_Optimization_(SEO)_Director/Salary/9436ce59/Content-Management",
                                "profileCount": 5,
                                "range": {
                                    "50": 70000
                                },
                                "isEstimated": null
                            }
                        ],
                        "parentUrl": null
                    }
                },
                "ratings": {
                    "Job Satisfaction Overall": {
                        "profileCount": 13,
                        "score": 4.25
                    }
                },
                "related": [
                    {
                        "name": "Operations Manager",
                        "url": "/research/US/Job=Operations_Manager/Salary",
                        "profileCount": 3502,
                        "range": {
                            "10": 46876.78,
                            "25": 57060.45,
                            "50": 71132.18,
                            "75": 89201.54,
                            "90": 111400.21
                        },
                        "average": null
                    },
                    {
                        "name": "Project Manager, (Unspecified Type / General)",
                        "url": "/research/US/Job=Project_Manager%2C_(Unspecified_Type_%2F_General)/Salary",
                        "profileCount": 3275,
                        "range": {
                            "10": 52442.34,
                            "25": 63803.53,
                            "50": 78740.64,
                            "75": 97464.19,
                            "90": 118798.09
                        },
                        "average": null
                    },
                    {
                        "name": "Director of Operations",
                        "url": "/research/US/Job=Director_of_Operations/Salary",
                        "profileCount": 1619,
                        "range": {
                            "10": 56993.89,
                            "25": 74249.71,
                            "50": 98759.14,
                            "75": 130704.48,
                            "90": 159840.11
                        },
                        "average": null
                    },
                    {
                        "name": "Project Engineer",
                        "url": "/research/US/Job=Project_Engineer/Salary",
                        "profileCount": 1397,
                        "range": {
                            "10": 56626.17,
                            "25": 64340.79,
                            "50": 73610.24,
                            "75": 86429.69,
                            "90": 102726.92
                        },
                        "average": null
                    },
                    {
                        "name": "Retail Store Manager",
                        "url": "/research/US/Job=Retail_Store_Manager/Salary",
                        "profileCount": 1352,
                        "range": {
                            "10": 37226.45,
                            "25": 43814.51,
                            "50": 52371.67,
                            "75": 63279.29,
                            "90": 75214.52
                        },
                        "average": null
                    },
                    {
                        "name": "Operations Supervisor",
                        "url": "/research/US/Job=Operations_Supervisor/Salary",
                        "profileCount": 1206,
                        "range": {
                            "10": 46241.28,
                            "25": 54074.16,
                            "50": 63037.13,
                            "75": 74384.17,
                            "90": 88639.65
                        },
                        "average": null
                    },
                    {
                        "name": "Mechanical Engineer",
                        "url": "/research/US/Job=Mechanical_Engineer/Salary",
                        "profileCount": 1088,
                        "range": {
                            "10": 59665.76,
                            "25": 67435.23,
                            "50": 77082.68,
                            "75": 90042.03,
                            "90": 106917.81
                        },
                        "average": null
                    },
                    {
                        "name": "Production Supervisor",
                        "url": "/research/US/Job=Production_Supervisor/Salary",
                        "profileCount": 1061,
                        "range": {
                            "10": 48741.53,
                            "25": 55857.44,
                            "50": 64846.35,
                            "75": 73931.63,
                            "90": 82954.64
                        },
                        "average": null
                    },
                    {
                        "name": "General / Operations Manager",
                        "url": "/research/US/Job=General_%2F_Operations_Manager/Salary",
                        "profileCount": 1043,
                        "range": {
                            "10": 42830.35,
                            "25": 54000.42,
                            "50": 71210.24,
                            "75": 95492.58,
                            "90": 123607.57
                        },
                        "average": null
                    },
                    {
                        "name": "Digital Marketing Manager",
                        "url": "/research/US/Job=Digital_Marketing_Manager/Salary",
                        "profileCount": 986,
                        "range": {
                            "10": 49331.63,
                            "25": 59656.9,
                            "50": 72627.51,
                            "75": 88422.7,
                            "90": 106037.62
                        },
                        "average": null
                    },
                    {
                        "name": "Information Technology (IT) Manager",
                        "url": "/research/US/Job=Information_Technology_(IT)_Manager/Salary",
                        "profileCount": 929,
                        "range": {
                            "10": 58345.92,
                            "25": 72201.7,
                            "50": 91280.1,
                            "75": 114966.03,
                            "90": 137085.65
                        },
                        "average": null
                    },
                    {
                        "name": "Marketing Manager",
                        "url": "/research/US/Job=Marketing_Manager/Salary",
                        "profileCount": 844,
                        "range": {
                            "10": 47762.65,
                            "25": 57815.43,
                            "50": 71283.38,
                            "75": 87440.32,
                            "90": 106115.88
                        },
                        "average": null
                    },
                    {
                        "name": "Project Manager, Information Technology (IT)",
                        "url": "/research/US/Job=Project_Manager%2C_Information_Technology_(IT)/Salary",
                        "profileCount": 844,
                        "range": {
                            "10": 59802.33,
                            "25": 73676.09,
                            "50": 91793.87,
                            "75": 112657.06,
                            "90": 133862.67
                        },
                        "average": null
                    },
                    {
                        "name": "Assistant Store Manager",
                        "url": "/research/US/Job=Assistant_Store_Manager/Hourly_Rate",
                        "profileCount": 809,
                        "range": {
                            "10": 37540.19,
                            "25": 44955.72,
                            "50": 52623.92,
                            "75": 60393.92,
                            "90": 67888.02
                        },
                        "average": null
                    },
                    {
                        "name": "Customer Service Supervisor",
                        "url": "/research/US/Job=Customer_Service_Supervisor/Hourly_Rate",
                        "profileCount": 741,
                        "range": {
                            "10": 40240.52,
                            "25": 47205.99,
                            "50": 55255.68,
                            "75": 64039.86,
                            "90": 73031.52
                        },
                        "average": null
                    },
                    {
                        "name": "Project Manager, Construction",
                        "url": "/research/US/Job=Project_Manager%2C_Construction/Salary",
                        "profileCount": 702,
                        "range": {
                            "10": 52009.67,
                            "25": 63427.06,
                            "50": 79959.02,
                            "75": 99736.07,
                            "90": 124040.42
                        },
                        "average": null
                    },
                    {
                        "name": "Retail Store Assistant Manager",
                        "url": "/research/US/Job=Retail_Store_Assistant_Manager/Hourly_Rate",
                        "profileCount": 693,
                        "range": {
                            "10": 33965.82,
                            "25": 41478.69,
                            "50": 50378.37,
                            "75": 59413.46,
                            "90": 67094.01
                        },
                        "average": null
                    },
                    {
                        "name": "Customer Service Manager",
                        "url": "/research/US/Job=Customer_Service_Manager/Salary",
                        "profileCount": 662,
                        "range": {
                            "10": 42929.26,
                            "25": 50874.2,
                            "50": 62081.54,
                            "75": 75459.02,
                            "90": 89164.89
                        },
                        "average": null
                    },
                    {
                        "name": "Information Technology (IT) Director",
                        "url": "/research/US/Job=Information_Technology_(IT)_Director/Salary",
                        "profileCount": 647,
                        "range": {
                            "10": 74041.18,
                            "25": 95795.34,
                            "50": 124712.68,
                            "75": 154187.29,
                            "90": 178926.55
                        },
                        "average": null
                    },
                    {
                        "name": "General Manager, Restaurant",
                        "url": "/research/US/Job=General_Manager%2C_Restaurant/Salary",
                        "profileCount": 642,
                        "range": {
                            "10": 38398.07,
                            "25": 44974.52,
                            "50": 53603.43,
                            "75": 63630.92,
                            "90": 74118.76
                        },
                        "average": null
                    }
                ],
                "benefits": null,
                "comparisons": null,
                "locations": null,
                "occupationalDetails": {
                    "@context": "http://schema.googleapis.com/",
                    "@id": "/research/US/Job=Search_Engine_Optimization_(SEO)_Director/Salary",
                    "occupationalCategory": "15-1080.00 - Network Systems and Data Communications Analysts",
                    "skills": "Search Engine Optimization (SEO), Team Leadership, Strategy, Google Analytics, Web Analytics, Online Marketing, Project Management, Search Engine Marketing (SEM), People Management, Content Management",
                    "educationRequirements": null,
                    "experienceRequirements": null,
                    "qualifications": null,
                    "responsibilities": null,
                    "mainEntityOfPage": {
                        "lastReviewed": "2023-08-09T10:08:12.38749Z",
                        "description": null,
                        "name": null,
                        "url": null,
                        "@type": "WebPage"
                    },
                    "occupationLocation": [
                        {
                            "description": null,
                            "name": "United States",
                            "url": null,
                            "@type": "Country"
                        }
                    ],
                    "estimatedSalary": [
                        {
                            "currency": "USD",
                            "unitText": null,
                            "duration": "P1Y",
                            "percentile10": "64114.93",
                            "percentile25": "80714.39",
                            "median": "99421.81",
                            "percentile75": "119907.06",
                            "percentile90": "150032.23",
                            "description": null,
                            "name": "total",
                            "url": null,
                            "@type": "MonetaryAmountDistribution"
                        },
                        {
                            "currency": "USD",
                            "unitText": null,
                            "duration": "P1Y",
                            "percentile10": "64779.27",
                            "percentile25": "78937.02",
                            "median": "96416.2",
                            "percentile75": "120439.17",
                            "percentile90": "146993.54",
                            "description": null,
                            "name": "base",
                            "url": null,
                            "@type": "MonetaryAmountDistribution"
                        },
                        {
                            "currency": "USD",
                            "unitText": null,
                            "duration": "P1Y",
                            "percentile10": "1089.06",
                            "percentile25": "2350",
                            "median": "7428.11",
                            "percentile75": "13500",
                            "percentile90": "29021.02",
                            "description": null,
                            "name": "bonus",
                            "url": null,
                            "@type": "MonetaryAmountDistribution"
                        }
                    ],
                    "sampleSize": 109,
                    "yearsExperienceMin": null,
                    "yearsExperienceMax": null,
                    "hiringOrganization": null,
                    "description": "Search engine optimization (SEO) directors serve as innovators and often work in teams to brainstorm ideas for improving SEO for an organization's online presence. They are primarily responsible for supervising SEO employees and typically work in office settings, and attending meetings may be necessary on a regular basis.\r\nSEO directors work with a variety of staff, particularly project managers, so strong communication skills are important in this position, and many directors work for large tech companies such as Google, Microsoft, and Yahoo.\r\nA bachelor's degree in information technology (IT) or a related field and at least a few years of relevant experience are generally required for this position, and some employers may prefer those who also have prior leadership experience. Computer skills and proficiency in Microsoft Office programs are essential in this position, and strong communication skills are also important to work well with staff members and achieve goals in a timely manner. SEO directors typically work full-time, and some overtime may be necessary on occasion, so the ability to work under pressure and strict deadlines is highly beneficial.",
                    "name": "Search Engine Optimization (SEO) Director",
                    "url": "/research/US/Job=Search_Engine_Optimization_(SEO)_Director/Salary",
                    "@type": "OccupationAggregation"
                }
            }
        },
        "__N_SSP": true
    },
    "page": "/job/pay",
    "query": {},
    "buildId": "app",
    "assetPrefix": "https://cdn-payscale.com/content/research-center-web/prod/2023.1031.1908.342-master",
    "isFallback": false,
    "gssp": true,
    "customServer": true
}